setup.cfg
setup.py
hamming_hash/__init__.py
hamming_hash/hamming_hash.py
hamming_hash.egg-info/PKG-INFO
hamming_hash.egg-info/SOURCES.txt
hamming_hash.egg-info/dependency_links.txt
hamming_hash.egg-info/not-zip-safe
hamming_hash.egg-info/top_level.txt