Metadata-Version: 1.0
Name: hamming-hash
Version: 1.3
Summary: Distance Hamming between hash SHA-256
Home-page: UNKNOWN
Author: UNKNOWN
Author-email: formydiablo3@mai.ru
License: UNKNOWN
Platform: UNKNOWN
